open_geodata_api/__init__.py
open_geodata_api/cli/collections.py
open_geodata_api/cli/download.py
open_geodata_api/cli/items.py
open_geodata_api/cli/main.py
open_geodata_api/cli/search.py
open_geodata_api/cli/utils.py
open_geodata_api/core/__init__.py
open_geodata_api/core/assets.py
open_geodata_api/core/base_client.py
open_geodata_api/core/collections.py
open_geodata_api/core/items.py
open_geodata_api/core/search.py
open_geodata_api/earthsearch/__init__.py
open_geodata_api/earthsearch/client.py
open_geodata_api/earthsearch/validation.py
open_geodata_api/planetary/__init__.py
open_geodata_api/planetary/client.py
open_geodata_api/planetary/signing.py
open_geodata_api/unified/__init__.py
open_geodata_api/unified/client.py
open_geodata_api/unified/utils.py
open_geodata_api/unified/validation.py
open_geodata_api/utils/__init__.py
open_geodata_api/utils/analysis.py
open_geodata_api/utils/batch_processing.py
open_geodata_api/utils/config.py
open_geodata_api/utils/data_processing.py
open_geodata_api/utils/download.py
open_geodata_api/utils/error_handling.py
open_geodata_api/utils/filters.py
open_geodata_api/utils/url_management.py
open_geodata_api-0.4.2.dist-info/METADATA
open_geodata_api-0.4.2.dist-info/WHEEL
open_geodata_api-0.4.2.dist-info/entry_points.txt
open_geodata_api-0.4.2.dist-info/licenses/LICENSE
open_geodata_api-0.4.2.dist-info/RECORD
