Metadata-Version: 2.4
Name: open-geodata-api
Version: 0.4.2
Summary: Unified Python client for open geospatial data APIs: Planetary Computer, EarthSearch, and more
Project-URL: License, https://github.com/Mirjan-Ali-Sha/open-geodata-api/blob/main/LICENSE
Project-URL: Third-Party Notices, https://github.com/Mirjan-Ali-Sha/open-geodata-api/blob/main/THIRD_PARTY_NOTICES.md
Project-URL: Homepage, https://github.com/Mirjan-Ali-Sha/open-geodata-api
Project-URL: Documentation, https://open-geodata-api.readthedocs.io
Project-URL: Repository, https://github.com/Mirjan-Ali-Sha/open-geodata-api
Project-URL: Bug Reports, https://github.com/Mirjan-Ali-Sha/open-geodata-api/issues
Author-email: Mirjan Ali Sha <mastools.help@gmail.com>
License-Expression: MIT
License-File: LICENSE
Keywords: api-client,cli,earth-observation,earthsearch,geodata,geospatial,open-data,planetary-computer,remote-sensing,satellite,stac
Classifier: Development Status :: 4 - Beta
Classifier: Environment :: Console
Classifier: Intended Audience :: Developers
Classifier: Intended Audience :: Science/Research
Classifier: License :: OSI Approved :: MIT License
Classifier: Operating System :: OS Independent
Classifier: Programming Language :: Python :: 3
Classifier: Programming Language :: Python :: 3.8
Classifier: Programming Language :: Python :: 3.9
Classifier: Programming Language :: Python :: 3.10
Classifier: Programming Language :: Python :: 3.11
Classifier: Programming Language :: Python :: 3.12
Classifier: Topic :: Internet :: WWW/HTTP :: Dynamic Content
Classifier: Topic :: Scientific/Engineering :: GIS
Classifier: Topic :: Software Development :: Libraries :: Python Modules
Requires-Python: >=3.8
Requires-Dist: click>=8.0.0
Requires-Dist: pandas>=1.3.0
Requires-Dist: planetary-computer>=1.0.0
Requires-Dist: requests>=2.25.0
Requires-Dist: tqdm>=4.67.1
Provides-Extra: cli
Requires-Dist: click>=8.0.0; extra == 'cli'
Requires-Dist: planetary-computer>=1.0.0; extra == 'cli'
Requires-Dist: requests>=2.25.0; extra == 'cli'
Requires-Dist: tqdm>=4.67.1; extra == 'cli'
Provides-Extra: complete
Requires-Dist: geopandas>=0.10.0; extra == 'complete'
Requires-Dist: rasterio>=1.3.0; extra == 'complete'
Requires-Dist: rioxarray>=0.11.0; extra == 'complete'
Requires-Dist: shapely>=1.8.0; extra == 'complete'
Requires-Dist: xarray>=0.19.0; extra == 'complete'
Provides-Extra: dev
Requires-Dist: black; extra == 'dev'
Requires-Dist: flake8; extra == 'dev'
Requires-Dist: mypy; extra == 'dev'
Requires-Dist: pytest-cov; extra == 'dev'
Requires-Dist: pytest>=6.0; extra == 'dev'
Requires-Dist: sphinx; extra == 'dev'
Requires-Dist: sphinx-rtd-theme; extra == 'dev'
Provides-Extra: io
Requires-Dist: rasterio>=1.3.0; extra == 'io'
Requires-Dist: rioxarray>=0.11.0; extra == 'io'
Requires-Dist: xarray>=0.19.0; extra == 'io'
Provides-Extra: none
Provides-Extra: spatial
Requires-Dist: geopandas>=0.10.0; extra == 'spatial'
Requires-Dist: shapely>=1.8.0; extra == 'spatial'
